kagglog/__init__.py
kagglog/logger.py
kagglog-0.2.1.dist-info/licenses/LICENSE
kagglog-0.2.1.dist-info/METADATA
kagglog-0.2.1.dist-info/WHEEL
kagglog-0.2.1.dist-info/top_level.txt
kagglog-0.2.1.dist-info/RECORD
